{"nodes": [{"id": "d_scroller_plethora_bit_starter_puzzle_bits_gen_nurikabe6_js", "label": "gen_nurikabe6.js", "file_type": "code", "source_file": "D:\\Scroller\\plethora-bit-starter\\puzzle-bits\\gen_nurikabe6.js", "source_location": "L1"}, {"id": "gen_nurikabe6_validatenurikabe", "label": "validateNurikabe()", "file_type": "code", "source_file": "D:\\Scroller\\plethora-bit-starter\\puzzle-bits\\gen_nurikabe6.js", "source_location": "L3"}, {"id": "gen_nurikabe6_test", "label": "test()", "file_type": "code", "source_file": "D:\\Scroller\\plethora-bit-starter\\puzzle-bits\\gen_nurikabe6.js", "source_location": "L43"}], "edges": [{"source": "d_scroller_plethora_bit_starter_puzzle_bits_gen_nurikabe6_js", "target": "gen_nurikabe6_validatenurikabe", "relation": "contains", "confidence": "EXTRACTED", "source_file": "D:\\Scroller\\plethora-bit-starter\\puzzle-bits\\gen_nurikabe6.js", "source_location": "L3", "weight": 1.0}, {"source": "d_scroller_plethora_bit_starter_puzzle_bits_gen_nurikabe6_js", "target": "gen_nurikabe6_test", "relation": "contains", "confidence": "EXTRACTED", "source_file": "D:\\Scroller\\plethora-bit-starter\\puzzle-bits\\gen_nurikabe6.js", "source_location": "L43", "weight": 1.0}, {"source": "gen_nurikabe6_test", "target": "gen_nurikabe6_validatenurikabe", "relation": "calls", "confidence": "EXTRACTED", "source_file": "D:\\Scroller\\plethora-bit-starter\\puzzle-bits\\gen_nurikabe6.js", "source_location": "L65", "weight": 1.0}], "raw_calls": [{"caller_nid": "gen_nurikabe6_validatenurikabe", "callee": "from", "source_file": "D:\\Scroller\\plethora-bit-starter\\puzzle-bits\\gen_nurikabe6.js", "source_location": "L7"}, {"caller_nid": "gen_nurikabe6_validatenurikabe", "callee": "pop", "source_file": "D:\\Scroller\\plethora-bit-starter\\puzzle-bits\\gen_nurikabe6.js", "source_location": "L13"}, {"caller_nid": "gen_nurikabe6_validatenurikabe", "callee": "push", "source_file": "D:\\Scroller\\plethora-bit-starter\\puzzle-bits\\gen_nurikabe6.js", "source_location": "L13"}, {"caller_nid": "gen_nurikabe6_validatenurikabe", "callee": "push", "source_file": "D:\\Scroller\\plethora-bit-starter\\puzzle-bits\\gen_nurikabe6.js", "source_location": "L17"}, {"caller_nid": "gen_nurikabe6_validatenurikabe", "callee": "push", "source_file": "D:\\Scroller\\plethora-bit-starter\\puzzle-bits\\gen_nurikabe6.js", "source_location": "L25"}, {"caller_nid": "gen_nurikabe6_validatenurikabe", "callee": "add", "source_file": "D:\\Scroller\\plethora-bit-starter\\puzzle-bits\\gen_nurikabe6.js", "source_location": "L27"}, {"caller_nid": "gen_nurikabe6_validatenurikabe", "callee": "join", "source_file": "D:\\Scroller\\plethora-bit-starter\\puzzle-bits\\gen_nurikabe6.js", "source_location": "L27"}, {"caller_nid": "gen_nurikabe6_validatenurikabe", "callee": "pop", "source_file": "D:\\Scroller\\plethora-bit-starter\\puzzle-bits\\gen_nurikabe6.js", "source_location": "L29"}, {"caller_nid": "gen_nurikabe6_validatenurikabe", "callee": "has", "source_file": "D:\\Scroller\\plethora-bit-starter\\puzzle-bits\\gen_nurikabe6.js", "source_location": "L32"}, {"caller_nid": "gen_nurikabe6_validatenurikabe", "callee": "add", "source_file": "D:\\Scroller\\plethora-bit-starter\\puzzle-bits\\gen_nurikabe6.js", "source_location": "L32"}, {"caller_nid": "gen_nurikabe6_validatenurikabe", "callee": "push", "source_file": "D:\\Scroller\\plethora-bit-starter\\puzzle-bits\\gen_nurikabe6.js", "source_location": "L32"}, {"caller_nid": "gen_nurikabe6_test", "callee": "from", "source_file": "D:\\Scroller\\plethora-bit-starter\\puzzle-bits\\gen_nurikabe6.js", "source_location": "L44"}, {"caller_nid": "gen_nurikabe6_test", "callee": "from", "source_file": "D:\\Scroller\\plethora-bit-starter\\puzzle-bits\\gen_nurikabe6.js", "source_location": "L45"}, {"caller_nid": "gen_nurikabe6_test", "callee": "map", "source_file": "D:\\Scroller\\plethora-bit-starter\\puzzle-bits\\gen_nurikabe6.js", "source_location": "L46"}, {"caller_nid": "gen_nurikabe6_test", "callee": "split", "source_file": "D:\\Scroller\\plethora-bit-starter\\puzzle-bits\\gen_nurikabe6.js", "source_location": "L53"}, {"caller_nid": "gen_nurikabe6_test", "callee": "abs", "source_file": "D:\\Scroller\\plethora-bit-starter\\puzzle-bits\\gen_nurikabe6.js", "source_location": "L55"}, {"caller_nid": "gen_nurikabe6_test", "callee": "abs", "source_file": "D:\\Scroller\\plethora-bit-starter\\puzzle-bits\\gen_nurikabe6.js", "source_location": "L55"}, {"caller_nid": "gen_nurikabe6_test", "callee": "has", "source_file": "D:\\Scroller\\plethora-bit-starter\\puzzle-bits\\gen_nurikabe6.js", "source_location": "L57"}, {"caller_nid": "gen_nurikabe6_test", "callee": "log", "source_file": "D:\\Scroller\\plethora-bit-starter\\puzzle-bits\\gen_nurikabe6.js", "source_location": "L58"}, {"caller_nid": "gen_nurikabe6_test", "callee": "log", "source_file": "D:\\Scroller\\plethora-bit-starter\\puzzle-bits\\gen_nurikabe6.js", "source_location": "L66"}, {"caller_nid": "gen_nurikabe6_test", "callee": "log", "source_file": "D:\\Scroller\\plethora-bit-starter\\puzzle-bits\\gen_nurikabe6.js", "source_location": "L68"}, {"caller_nid": "gen_nurikabe6_test", "callee": "log", "source_file": "D:\\Scroller\\plethora-bit-starter\\puzzle-bits\\gen_nurikabe6.js", "source_location": "L69"}, {"caller_nid": "gen_nurikabe6_test", "callee": "stringify", "source_file": "D:\\Scroller\\plethora-bit-starter\\puzzle-bits\\gen_nurikabe6.js", "source_location": "L69"}, {"caller_nid": "gen_nurikabe6_test", "callee": "log", "source_file": "D:\\Scroller\\plethora-bit-starter\\puzzle-bits\\gen_nurikabe6.js", "source_location": "L70"}, {"caller_nid": "gen_nurikabe6_test", "callee": "stringify", "source_file": "D:\\Scroller\\plethora-bit-starter\\puzzle-bits\\gen_nurikabe6.js", "source_location": "L70"}]}