{"nodes": [{"id": "d_scroller_plethora_bit_starter_jsgame_bits_onoff_js", "label": "onoff.js", "file_type": "code", "source_file": "D:\\Scroller\\plethora-bit-starter\\jsgame-bits\\onoff.js", "source_location": "L1"}, {"id": "onoff_init", "label": "init()", "file_type": "code", "source_file": "D:\\Scroller\\plethora-bit-starter\\jsgame-bits\\onoff.js", "source_location": "L11"}, {"id": "onoff_pause", "label": "pause()", "file_type": "code", "source_file": "D:\\Scroller\\plethora-bit-starter\\jsgame-bits\\onoff.js", "source_location": "L433"}, {"id": "onoff_resume", "label": "resume()", "file_type": "code", "source_file": "D:\\Scroller\\plethora-bit-starter\\jsgame-bits\\onoff.js", "source_location": "L434"}], "edges": [{"source": "d_scroller_plethora_bit_starter_jsgame_bits_onoff_js", "target": "onoff_init", "relation": "contains", "confidence": "EXTRACTED", "source_file": "D:\\Scroller\\plethora-bit-starter\\jsgame-bits\\onoff.js", "source_location": "L11", "weight": 1.0}, {"source": "d_scroller_plethora_bit_starter_jsgame_bits_onoff_js", "target": "onoff_pause", "relation": "contains", "confidence": "EXTRACTED", "source_file": "D:\\Scroller\\plethora-bit-starter\\jsgame-bits\\onoff.js", "source_location": "L433", "weight": 1.0}, {"source": "d_scroller_plethora_bit_starter_jsgame_bits_onoff_js", "target": "onoff_resume", "relation": "contains", "confidence": "EXTRACTED", "source_file": "D:\\Scroller\\plethora-bit-starter\\jsgame-bits\\onoff.js", "source_location": "L434", "weight": 1.0}], "raw_calls": [{"caller_nid": "onoff_init", "callee": "createCanvas2D", "source_file": "D:\\Scroller\\plethora-bit-starter\\jsgame-bits\\onoff.js", "source_location": "L14"}, {"caller_nid": "onoff_init", "callee": "getContext", "source_file": "D:\\Scroller\\plethora-bit-starter\\jsgame-bits\\onoff.js", "source_location": "L15"}, {"caller_nid": "onoff_init", "callee": "get", "source_file": "D:\\Scroller\\plethora-bit-starter\\jsgame-bits\\onoff.js", "source_location": "L48"}, {"caller_nid": "onoff_init", "callee": "min", "source_file": "D:\\Scroller\\plethora-bit-starter\\jsgame-bits\\onoff.js", "source_location": "L174"}, {"caller_nid": "onoff_init", "callee": "floor", "source_file": "D:\\Scroller\\plethora-bit-starter\\jsgame-bits\\onoff.js", "source_location": "L175"}, {"caller_nid": "onoff_init", "callee": "loadLevel", "source_file": "D:\\Scroller\\plethora-bit-starter\\jsgame-bits\\onoff.js", "source_location": "L189"}, {"caller_nid": "onoff_init", "callee": "listen", "source_file": "D:\\Scroller\\plethora-bit-starter\\jsgame-bits\\onoff.js", "source_location": "L192"}, {"caller_nid": "onoff_init", "callee": "listen", "source_file": "D:\\Scroller\\plethora-bit-starter\\jsgame-bits\\onoff.js", "source_location": "L254"}, {"caller_nid": "onoff_init", "callee": "raf", "source_file": "D:\\Scroller\\plethora-bit-starter\\jsgame-bits\\onoff.js", "source_location": "L257"}, {"caller_nid": "onoff_init", "callee": "ready", "source_file": "D:\\Scroller\\plethora-bit-starter\\jsgame-bits\\onoff.js", "source_location": "L430"}]}