{"nodes": [{"id": "d_scroller_plethora_bit_starter_game_bits_tower_smash_js", "label": "tower_smash.js", "file_type": "code", "source_file": "D:\\Scroller\\plethora-bit-starter\\game_bits\\tower_smash.js", "source_location": "L1"}, {"id": "tower_smash_init", "label": "init()", "file_type": "code", "source_file": "D:\\Scroller\\plethora-bit-starter\\game_bits\\tower_smash.js", "source_location": "L32"}, {"id": "tower_smash_loadpc", "label": "_loadPC()", "file_type": "code", "source_file": "D:\\Scroller\\plethora-bit-starter\\game_bits\\tower_smash.js", "source_location": "L89"}, {"id": "tower_smash_loadammo", "label": "_loadAmmo()", "file_type": "code", "source_file": "D:\\Scroller\\plethora-bit-starter\\game_bits\\tower_smash.js", "source_location": "L98"}, {"id": "tower_smash_startgame", "label": "_startGame()", "file_type": "code", "source_file": "D:\\Scroller\\plethora-bit-starter\\game_bits\\tower_smash.js", "source_location": "L107"}, {"id": "tower_smash_buildtower", "label": "_buildTower()", "file_type": "code", "source_file": "D:\\Scroller\\plethora-bit-starter\\game_bits\\tower_smash.js", "source_location": "L209"}, {"id": "tower_smash_clearblocks", "label": "_clearBlocks()", "file_type": "code", "source_file": "D:\\Scroller\\plethora-bit-starter\\game_bits\\tower_smash.js", "source_location": "L261"}, {"id": "tower_smash_createballentity", "label": "_createBallEntity()", "file_type": "code", "source_file": "D:\\Scroller\\plethora-bit-starter\\game_bits\\tower_smash.js", "source_location": "L271"}, {"id": "tower_smash_launchball", "label": "_launchBall()", "file_type": "code", "source_file": "D:\\Scroller\\plethora-bit-starter\\game_bits\\tower_smash.js", "source_location": "L303"}, {"id": "tower_smash_bindinput", "label": "_bindInput()", "file_type": "code", "source_file": "D:\\Scroller\\plethora-bit-starter\\game_bits\\tower_smash.js", "source_location": "L342"}, {"id": "tower_smash_showaim", "label": "_showAim()", "file_type": "code", "source_file": "D:\\Scroller\\plethora-bit-starter\\game_bits\\tower_smash.js", "source_location": "L378"}, {"id": "tower_smash_onupdate", "label": "_onUpdate()", "file_type": "code", "source_file": "D:\\Scroller\\plethora-bit-starter\\game_bits\\tower_smash.js", "source_location": "L389"}, {"id": "tower_smash_checkblocks", "label": "_checkBlocks()", "file_type": "code", "source_file": "D:\\Scroller\\plethora-bit-starter\\game_bits\\tower_smash.js", "source_location": "L395"}, {"id": "tower_smash_checkwin", "label": "_checkWin()", "file_type": "code", "source_file": "D:\\Scroller\\plethora-bit-starter\\game_bits\\tower_smash.js", "source_location": "L413"}, {"id": "tower_smash_updatescoreui", "label": "_updateScoreUI()", "file_type": "code", "source_file": "D:\\Scroller\\plethora-bit-starter\\game_bits\\tower_smash.js", "source_location": "L423"}, {"id": "tower_smash_showsmashed", "label": "_showSmashed()", "file_type": "code", "source_file": "D:\\Scroller\\plethora-bit-starter\\game_bits\\tower_smash.js", "source_location": "L429"}, {"id": "tower_smash_initaudio", "label": "_initAudio()", "file_type": "code", "source_file": "D:\\Scroller\\plethora-bit-starter\\game_bits\\tower_smash.js", "source_location": "L443"}, {"id": "tower_smash_soundcannon", "label": "_soundCannon()", "file_type": "code", "source_file": "D:\\Scroller\\plethora-bit-starter\\game_bits\\tower_smash.js", "source_location": "L450"}, {"id": "tower_smash_soundimpact", "label": "_soundImpact()", "file_type": "code", "source_file": "D:\\Scroller\\plethora-bit-starter\\game_bits\\tower_smash.js", "source_location": "L472"}, {"id": "tower_smash_soundscore", "label": "_soundScore()", "file_type": "code", "source_file": "D:\\Scroller\\plethora-bit-starter\\game_bits\\tower_smash.js", "source_location": "L489"}, {"id": "tower_smash_soundvictory", "label": "_soundVictory()", "file_type": "code", "source_file": "D:\\Scroller\\plethora-bit-starter\\game_bits\\tower_smash.js", "source_location": "L503"}, {"id": "tower_smash_destroy", "label": "destroy()", "file_type": "code", "source_file": "D:\\Scroller\\plethora-bit-starter\\game_bits\\tower_smash.js", "source_location": "L521"}], "edges": [{"source": "d_scroller_plethora_bit_starter_game_bits_tower_smash_js", "target": "tower_smash_init", "relation": "contains", "confidence": "EXTRACTED", "source_file": "D:\\Scroller\\plethora-bit-starter\\game_bits\\tower_smash.js", "source_location": "L32", "weight": 1.0}, {"source": "d_scroller_plethora_bit_starter_game_bits_tower_smash_js", "target": "tower_smash_loadpc", "relation": "contains", "confidence": "EXTRACTED", "source_file": "D:\\Scroller\\plethora-bit-starter\\game_bits\\tower_smash.js", "source_location": "L89", "weight": 1.0}, {"source": "d_scroller_plethora_bit_starter_game_bits_tower_smash_js", "target": "tower_smash_loadammo", "relation": "contains", "confidence": "EXTRACTED", "source_file": "D:\\Scroller\\plethora-bit-starter\\game_bits\\tower_smash.js", "source_location": "L98", "weight": 1.0}, {"source": "d_scroller_plethora_bit_starter_game_bits_tower_smash_js", "target": "tower_smash_startgame", "relation": "contains", "confidence": "EXTRACTED", "source_file": "D:\\Scroller\\plethora-bit-starter\\game_bits\\tower_smash.js", "source_location": "L107", "weight": 1.0}, {"source": "d_scroller_plethora_bit_starter_game_bits_tower_smash_js", "target": "tower_smash_buildtower", "relation": "contains", "confidence": "EXTRACTED", "source_file": "D:\\Scroller\\plethora-bit-starter\\game_bits\\tower_smash.js", "source_location": "L209", "weight": 1.0}, {"source": "d_scroller_plethora_bit_starter_game_bits_tower_smash_js", "target": "tower_smash_clearblocks", "relation": "contains", "confidence": "EXTRACTED", "source_file": "D:\\Scroller\\plethora-bit-starter\\game_bits\\tower_smash.js", "source_location": "L261", "weight": 1.0}, {"source": "d_scroller_plethora_bit_starter_game_bits_tower_smash_js", "target": "tower_smash_createballentity", "relation": "contains", "confidence": "EXTRACTED", "source_file": "D:\\Scroller\\plethora-bit-starter\\game_bits\\tower_smash.js", "source_location": "L271", "weight": 1.0}, {"source": "d_scroller_plethora_bit_starter_game_bits_tower_smash_js", "target": "tower_smash_launchball", "relation": "contains", "confidence": "EXTRACTED", "source_file": "D:\\Scroller\\plethora-bit-starter\\game_bits\\tower_smash.js", "source_location": "L303", "weight": 1.0}, {"source": "d_scroller_plethora_bit_starter_game_bits_tower_smash_js", "target": "tower_smash_bindinput", "relation": "contains", "confidence": "EXTRACTED", "source_file": "D:\\Scroller\\plethora-bit-starter\\game_bits\\tower_smash.js", "source_location": "L342", "weight": 1.0}, {"source": "d_scroller_plethora_bit_starter_game_bits_tower_smash_js", "target": "tower_smash_showaim", "relation": "contains", "confidence": "EXTRACTED", "source_file": "D:\\Scroller\\plethora-bit-starter\\game_bits\\tower_smash.js", "source_location": "L378", "weight": 1.0}, {"source": "d_scroller_plethora_bit_starter_game_bits_tower_smash_js", "target": "tower_smash_onupdate", "relation": "contains", "confidence": "EXTRACTED", "source_file": "D:\\Scroller\\plethora-bit-starter\\game_bits\\tower_smash.js", "source_location": "L389", "weight": 1.0}, {"source": "d_scroller_plethora_bit_starter_game_bits_tower_smash_js", "target": "tower_smash_checkblocks", "relation": "contains", "confidence": "EXTRACTED", "source_file": "D:\\Scroller\\plethora-bit-starter\\game_bits\\tower_smash.js", "source_location": "L395", "weight": 1.0}, {"source": "d_scroller_plethora_bit_starter_game_bits_tower_smash_js", "target": "tower_smash_checkwin", "relation": "contains", "confidence": "EXTRACTED", "source_file": "D:\\Scroller\\plethora-bit-starter\\game_bits\\tower_smash.js", "source_location": "L413", "weight": 1.0}, {"source": "d_scroller_plethora_bit_starter_game_bits_tower_smash_js", "target": "tower_smash_updatescoreui", "relation": "contains", "confidence": "EXTRACTED", "source_file": "D:\\Scroller\\plethora-bit-starter\\game_bits\\tower_smash.js", "source_location": "L423", "weight": 1.0}, {"source": "d_scroller_plethora_bit_starter_game_bits_tower_smash_js", "target": "tower_smash_showsmashed", "relation": "contains", "confidence": "EXTRACTED", "source_file": "D:\\Scroller\\plethora-bit-starter\\game_bits\\tower_smash.js", "source_location": "L429", "weight": 1.0}, {"source": "d_scroller_plethora_bit_starter_game_bits_tower_smash_js", "target": "tower_smash_initaudio", "relation": "contains", "confidence": "EXTRACTED", "source_file": "D:\\Scroller\\plethora-bit-starter\\game_bits\\tower_smash.js", "source_location": "L443", "weight": 1.0}, {"source": "d_scroller_plethora_bit_starter_game_bits_tower_smash_js", "target": "tower_smash_soundcannon", "relation": "contains", "confidence": "EXTRACTED", "source_file": "D:\\Scroller\\plethora-bit-starter\\game_bits\\tower_smash.js", "source_location": "L450", "weight": 1.0}, {"source": "d_scroller_plethora_bit_starter_game_bits_tower_smash_js", "target": "tower_smash_soundimpact", "relation": "contains", "confidence": "EXTRACTED", "source_file": "D:\\Scroller\\plethora-bit-starter\\game_bits\\tower_smash.js", "source_location": "L472", "weight": 1.0}, {"source": "d_scroller_plethora_bit_starter_game_bits_tower_smash_js", "target": "tower_smash_soundscore", "relation": "contains", "confidence": "EXTRACTED", "source_file": "D:\\Scroller\\plethora-bit-starter\\game_bits\\tower_smash.js", "source_location": "L489", "weight": 1.0}, {"source": "d_scroller_plethora_bit_starter_game_bits_tower_smash_js", "target": "tower_smash_soundvictory", "relation": "contains", "confidence": "EXTRACTED", "source_file": "D:\\Scroller\\plethora-bit-starter\\game_bits\\tower_smash.js", "source_location": "L503", "weight": 1.0}, {"source": "d_scroller_plethora_bit_starter_game_bits_tower_smash_js", "target": "tower_smash_destroy", "relation": "contains", "confidence": "EXTRACTED", "source_file": "D:\\Scroller\\plethora-bit-starter\\game_bits\\tower_smash.js", "source_location": "L521", "weight": 1.0}, {"source": "tower_smash_init", "target": "tower_smash_loadpc", "relation": "calls", "confidence": "EXTRACTED", "source_file": "D:\\Scroller\\plethora-bit-starter\\game_bits\\tower_smash.js", "source_location": "L86", "weight": 1.0}, {"source": "tower_smash_startgame", "target": "tower_smash_bindinput", "relation": "calls", "confidence": "EXTRACTED", "source_file": "D:\\Scroller\\plethora-bit-starter\\game_bits\\tower_smash.js", "source_location": "L181", "weight": 1.0}, {"source": "tower_smash_buildtower", "target": "tower_smash_updatescoreui", "relation": "calls", "confidence": "EXTRACTED", "source_file": "D:\\Scroller\\plethora-bit-starter\\game_bits\\tower_smash.js", "source_location": "L258", "weight": 1.0}, {"source": "tower_smash_clearblocks", "target": "tower_smash_destroy", "relation": "calls", "confidence": "EXTRACTED", "source_file": "D:\\Scroller\\plethora-bit-starter\\game_bits\\tower_smash.js", "source_location": "L263", "weight": 1.0}, {"source": "tower_smash_launchball", "target": "tower_smash_initaudio", "relation": "calls", "confidence": "EXTRACTED", "source_file": "D:\\Scroller\\plethora-bit-starter\\game_bits\\tower_smash.js", "source_location": "L323", "weight": 1.0}, {"source": "tower_smash_launchball", "target": "tower_smash_soundcannon", "relation": "calls", "confidence": "EXTRACTED", "source_file": "D:\\Scroller\\plethora-bit-starter\\game_bits\\tower_smash.js", "source_location": "L324", "weight": 1.0}, {"source": "tower_smash_onupdate", "target": "tower_smash_checkblocks", "relation": "calls", "confidence": "EXTRACTED", "source_file": "D:\\Scroller\\plethora-bit-starter\\game_bits\\tower_smash.js", "source_location": "L391", "weight": 1.0}, {"source": "tower_smash_onupdate", "target": "tower_smash_checkwin", "relation": "calls", "confidence": "EXTRACTED", "source_file": "D:\\Scroller\\plethora-bit-starter\\game_bits\\tower_smash.js", "source_location": "L392", "weight": 1.0}, {"source": "tower_smash_checkblocks", "target": "tower_smash_updatescoreui", "relation": "calls", "confidence": "EXTRACTED", "source_file": "D:\\Scroller\\plethora-bit-starter\\game_bits\\tower_smash.js", "source_location": "L403", "weight": 1.0}, {"source": "tower_smash_checkblocks", "target": "tower_smash_soundscore", "relation": "calls", "confidence": "EXTRACTED", "source_file": "D:\\Scroller\\plethora-bit-starter\\game_bits\\tower_smash.js", "source_location": "L407", "weight": 1.0}, {"source": "tower_smash_checkwin", "target": "tower_smash_showsmashed", "relation": "calls", "confidence": "EXTRACTED", "source_file": "D:\\Scroller\\plethora-bit-starter\\game_bits\\tower_smash.js", "source_location": "L417", "weight": 1.0}, {"source": "tower_smash_showsmashed", "target": "tower_smash_soundvictory", "relation": "calls", "confidence": "EXTRACTED", "source_file": "D:\\Scroller\\plethora-bit-starter\\game_bits\\tower_smash.js", "source_location": "L431", "weight": 1.0}], "raw_calls": [{"caller_nid": "tower_smash_init", "callee": "createElement", "source_file": "D:\\Scroller\\plethora-bit-starter\\game_bits\\tower_smash.js", "source_location": "L43"}, {"caller_nid": "tower_smash_init", "callee": "appendChild", "source_file": "D:\\Scroller\\plethora-bit-starter\\game_bits\\tower_smash.js", "source_location": "L53"}, {"caller_nid": "tower_smash_init", "callee": "createElement", "source_file": "D:\\Scroller\\plethora-bit-starter\\game_bits\\tower_smash.js", "source_location": "L56"}, {"caller_nid": "tower_smash_init", "callee": "appendChild", "source_file": "D:\\Scroller\\plethora-bit-starter\\game_bits\\tower_smash.js", "source_location": "L65"}, {"caller_nid": "tower_smash_init", "callee": "createElement", "source_file": "D:\\Scroller\\plethora-bit-starter\\game_bits\\tower_smash.js", "source_location": "L68"}, {"caller_nid": "tower_smash_init", "callee": "appendChild", "source_file": "D:\\Scroller\\plethora-bit-starter\\game_bits\\tower_smash.js", "source_location": "L76"}, {"caller_nid": "tower_smash_init", "callee": "createElement", "source_file": "D:\\Scroller\\plethora-bit-starter\\game_bits\\tower_smash.js", "source_location": "L79"}, {"caller_nid": "tower_smash_init", "callee": "appendChild", "source_file": "D:\\Scroller\\plethora-bit-starter\\game_bits\\tower_smash.js", "source_location": "L83"}, {"caller_nid": "tower_smash_loadpc", "callee": "cb", "source_file": "D:\\Scroller\\plethora-bit-starter\\game_bits\\tower_smash.js", "source_location": "L90"}, {"caller_nid": "tower_smash_loadpc", "callee": "createElement", "source_file": "D:\\Scroller\\plethora-bit-starter\\game_bits\\tower_smash.js", "source_location": "L91"}, {"caller_nid": "tower_smash_loadpc", "callee": "appendChild", "source_file": "D:\\Scroller\\plethora-bit-starter\\game_bits\\tower_smash.js", "source_location": "L95"}, {"caller_nid": "tower_smash_loadammo", "callee": "cb", "source_file": "D:\\Scroller\\plethora-bit-starter\\game_bits\\tower_smash.js", "source_location": "L99"}, {"caller_nid": "tower_smash_loadammo", "callee": "createElement", "source_file": "D:\\Scroller\\plethora-bit-starter\\game_bits\\tower_smash.js", "source_location": "L100"}, {"caller_nid": "tower_smash_loadammo", "callee": "appendChild", "source_file": "D:\\Scroller\\plethora-bit-starter\\game_bits\\tower_smash.js", "source_location": "L104"}, {"caller_nid": "tower_smash_startgame", "callee": "setCanvasFillMode", "source_file": "D:\\Scroller\\plethora-bit-starter\\game_bits\\tower_smash.js", "source_location": "L118"}, {"caller_nid": "tower_smash_startgame", "callee": "setCanvasResolution", "source_file": "D:\\Scroller\\plethora-bit-starter\\game_bits\\tower_smash.js", "source_location": "L119"}, {"caller_nid": "tower_smash_startgame", "callee": "set", "source_file": "D:\\Scroller\\plethora-bit-starter\\game_bits\\tower_smash.js", "source_location": "L125"}, {"caller_nid": "tower_smash_startgame", "callee": "addComponent", "source_file": "D:\\Scroller\\plethora-bit-starter\\game_bits\\tower_smash.js", "source_location": "L130"}, {"caller_nid": "tower_smash_startgame", "callee": "setPosition", "source_file": "D:\\Scroller\\plethora-bit-starter\\game_bits\\tower_smash.js", "source_location": "L136"}, {"caller_nid": "tower_smash_startgame", "callee": "lookAt", "source_file": "D:\\Scroller\\plethora-bit-starter\\game_bits\\tower_smash.js", "source_location": "L137"}, {"caller_nid": "tower_smash_startgame", "callee": "addChild", "source_file": "D:\\Scroller\\plethora-bit-starter\\game_bits\\tower_smash.js", "source_location": "L138"}, {"caller_nid": "tower_smash_startgame", "callee": "addComponent", "source_file": "D:\\Scroller\\plethora-bit-starter\\game_bits\\tower_smash.js", "source_location": "L142"}, {"caller_nid": "tower_smash_startgame", "callee": "setEulerAngles", "source_file": "D:\\Scroller\\plethora-bit-starter\\game_bits\\tower_smash.js", "source_location": "L150"}, {"caller_nid": "tower_smash_startgame", "callee": "addChild", "source_file": "D:\\Scroller\\plethora-bit-starter\\game_bits\\tower_smash.js", "source_location": "L151"}, {"caller_nid": "tower_smash_startgame", "callee": "addComponent", "source_file": "D:\\Scroller\\plethora-bit-starter\\game_bits\\tower_smash.js", "source_location": "L155"}, {"caller_nid": "tower_smash_startgame", "callee": "setPosition", "source_file": "D:\\Scroller\\plethora-bit-starter\\game_bits\\tower_smash.js", "source_location": "L161"}, {"caller_nid": "tower_smash_startgame", "callee": "addChild", "source_file": "D:\\Scroller\\plethora-bit-starter\\game_bits\\tower_smash.js", "source_location": "L162"}, {"caller_nid": "tower_smash_startgame", "callee": "addComponent", "source_file": "D:\\Scroller\\plethora-bit-starter\\game_bits\\tower_smash.js", "source_location": "L166"}, {"caller_nid": "tower_smash_startgame", "callee": "update", "source_file": "D:\\Scroller\\plethora-bit-starter\\game_bits\\tower_smash.js", "source_location": "L170"}, {"caller_nid": "tower_smash_startgame", "callee": "setLocalScale", "source_file": "D:\\Scroller\\plethora-bit-starter\\game_bits\\tower_smash.js", "source_location": "L172"}, {"caller_nid": "tower_smash_startgame", "callee": "setPosition", "source_file": "D:\\Scroller\\plethora-bit-starter\\game_bits\\tower_smash.js", "source_location": "L173"}, {"caller_nid": "tower_smash_startgame", "callee": "addChild", "source_file": "D:\\Scroller\\plethora-bit-starter\\game_bits\\tower_smash.js", "source_location": "L174"}, {"caller_nid": "tower_smash_startgame", "callee": "addComponent", "source_file": "D:\\Scroller\\plethora-bit-starter\\game_bits\\tower_smash.js", "source_location": "L175"}, {"caller_nid": "tower_smash_startgame", "callee": "addComponent", "source_file": "D:\\Scroller\\plethora-bit-starter\\game_bits\\tower_smash.js", "source_location": "L176"}, {"caller_nid": "tower_smash_startgame", "callee": "on", "source_file": "D:\\Scroller\\plethora-bit-starter\\game_bits\\tower_smash.js", "source_location": "L183"}, {"caller_nid": "tower_smash_startgame", "callee": "start", "source_file": "D:\\Scroller\\plethora-bit-starter\\game_bits\\tower_smash.js", "source_location": "L184"}, {"caller_nid": "tower_smash_startgame", "callee": "setTimeout", "source_file": "D:\\Scroller\\plethora-bit-starter\\game_bits\\tower_smash.js", "source_location": "L187"}, {"caller_nid": "tower_smash_buildtower", "callee": "addComponent", "source_file": "D:\\Scroller\\plethora-bit-starter\\game_bits\\tower_smash.js", "source_location": "L221"}, {"caller_nid": "tower_smash_buildtower", "callee": "update", "source_file": "D:\\Scroller\\plethora-bit-starter\\game_bits\\tower_smash.js", "source_location": "L228"}, {"caller_nid": "tower_smash_buildtower", "callee": "setLocalScale", "source_file": "D:\\Scroller\\plethora-bit-starter\\game_bits\\tower_smash.js", "source_location": "L236"}, {"caller_nid": "tower_smash_buildtower", "callee": "setPosition", "source_file": "D:\\Scroller\\plethora-bit-starter\\game_bits\\tower_smash.js", "source_location": "L237"}, {"caller_nid": "tower_smash_buildtower", "callee": "addChild", "source_file": "D:\\Scroller\\plethora-bit-starter\\game_bits\\tower_smash.js", "source_location": "L239"}, {"caller_nid": "tower_smash_buildtower", "callee": "addComponent", "source_file": "D:\\Scroller\\plethora-bit-starter\\game_bits\\tower_smash.js", "source_location": "L240"}, {"caller_nid": "tower_smash_buildtower", "callee": "addComponent", "source_file": "D:\\Scroller\\plethora-bit-starter\\game_bits\\tower_smash.js", "source_location": "L248"}, {"caller_nid": "tower_smash_buildtower", "callee": "push", "source_file": "D:\\Scroller\\plethora-bit-starter\\game_bits\\tower_smash.js", "source_location": "L252"}, {"caller_nid": "tower_smash_createballentity", "callee": "addComponent", "source_file": "D:\\Scroller\\plethora-bit-starter\\game_bits\\tower_smash.js", "source_location": "L276"}, {"caller_nid": "tower_smash_createballentity", "callee": "update", "source_file": "D:\\Scroller\\plethora-bit-starter\\game_bits\\tower_smash.js", "source_location": "L283"}, {"caller_nid": "tower_smash_createballentity", "callee": "setLocalScale", "source_file": "D:\\Scroller\\plethora-bit-starter\\game_bits\\tower_smash.js", "source_location": "L285"}, {"caller_nid": "tower_smash_createballentity", "callee": "addChild", "source_file": "D:\\Scroller\\plethora-bit-starter\\game_bits\\tower_smash.js", "source_location": "L287"}, {"caller_nid": "tower_smash_createballentity", "callee": "addComponent", "source_file": "D:\\Scroller\\plethora-bit-starter\\game_bits\\tower_smash.js", "source_location": "L288"}, {"caller_nid": "tower_smash_createballentity", "callee": "addComponent", "source_file": "D:\\Scroller\\plethora-bit-starter\\game_bits\\tower_smash.js", "source_location": "L296"}, {"caller_nid": "tower_smash_launchball", "callee": "setPosition", "source_file": "D:\\Scroller\\plethora-bit-starter\\game_bits\\tower_smash.js", "source_location": "L312"}, {"caller_nid": "tower_smash_launchball", "callee": "teleport", "source_file": "D:\\Scroller\\plethora-bit-starter\\game_bits\\tower_smash.js", "source_location": "L316"}, {"caller_nid": "tower_smash_launchball", "callee": "applyImpulse", "source_file": "D:\\Scroller\\plethora-bit-starter\\game_bits\\tower_smash.js", "source_location": "L319"}, {"caller_nid": "tower_smash_launchball", "callee": "setTimeout", "source_file": "D:\\Scroller\\plethora-bit-starter\\game_bits\\tower_smash.js", "source_location": "L327"}, {"caller_nid": "tower_smash_launchball", "callee": "clearTimeout", "source_file": "D:\\Scroller\\plethora-bit-starter\\game_bits\\tower_smash.js", "source_location": "L332"}, {"caller_nid": "tower_smash_launchball", "callee": "setTimeout", "source_file": "D:\\Scroller\\plethora-bit-starter\\game_bits\\tower_smash.js", "source_location": "L333"}, {"caller_nid": "tower_smash_bindinput", "callee": "addEventListener", "source_file": "D:\\Scroller\\plethora-bit-starter\\game_bits\\tower_smash.js", "source_location": "L369"}, {"caller_nid": "tower_smash_bindinput", "callee": "addEventListener", "source_file": "D:\\Scroller\\plethora-bit-starter\\game_bits\\tower_smash.js", "source_location": "L370"}, {"caller_nid": "tower_smash_showaim", "callee": "clearTimeout", "source_file": "D:\\Scroller\\plethora-bit-starter\\game_bits\\tower_smash.js", "source_location": "L383"}, {"caller_nid": "tower_smash_showaim", "callee": "setTimeout", "source_file": "D:\\Scroller\\plethora-bit-starter\\game_bits\\tower_smash.js", "source_location": "L384"}, {"caller_nid": "tower_smash_checkblocks", "callee": "has", "source_file": "D:\\Scroller\\plethora-bit-starter\\game_bits\\tower_smash.js", "source_location": "L399"}, {"caller_nid": "tower_smash_checkblocks", "callee": "getPosition", "source_file": "D:\\Scroller\\plethora-bit-starter\\game_bits\\tower_smash.js", "source_location": "L400"}, {"caller_nid": "tower_smash_checkblocks", "callee": "add", "source_file": "D:\\Scroller\\plethora-bit-starter\\game_bits\\tower_smash.js", "source_location": "L401"}, {"caller_nid": "tower_smash_checkblocks", "callee": "now", "source_file": "D:\\Scroller\\plethora-bit-starter\\game_bits\\tower_smash.js", "source_location": "L404"}, {"caller_nid": "tower_smash_showsmashed", "callee": "setTimeout", "source_file": "D:\\Scroller\\plethora-bit-starter\\game_bits\\tower_smash.js", "source_location": "L432"}, {"caller_nid": "tower_smash_soundcannon", "callee": "createOscillator", "source_file": "D:\\Scroller\\plethora-bit-starter\\game_bits\\tower_smash.js", "source_location": "L453"}, {"caller_nid": "tower_smash_soundcannon", "callee": "createGain", "source_file": "D:\\Scroller\\plethora-bit-starter\\game_bits\\tower_smash.js", "source_location": "L454"}, {"caller_nid": "tower_smash_soundcannon", "callee": "connect", "source_file": "D:\\Scroller\\plethora-bit-starter\\game_bits\\tower_smash.js", "source_location": "L455"}, {"caller_nid": "tower_smash_soundcannon", "callee": "connect", "source_file": "D:\\Scroller\\plethora-bit-starter\\game_bits\\tower_smash.js", "source_location": "L455"}, {"caller_nid": "tower_smash_soundcannon", "callee": "setValueAtTime", "source_file": "D:\\Scroller\\plethora-bit-starter\\game_bits\\tower_smash.js", "source_location": "L457"}, {"caller_nid": "tower_smash_soundcannon", "callee": "exponentialRampToValueAtTime", "source_file": "D:\\Scroller\\plethora-bit-starter\\game_bits\\tower_smash.js", "source_location": "L458"}, {"caller_nid": "tower_smash_soundcannon", "callee": "setValueAtTime", "source_file": "D:\\Scroller\\plethora-bit-starter\\game_bits\\tower_smash.js", "source_location": "L459"}, {"caller_nid": "tower_smash_soundcannon", "callee": "exponentialRampToValueAtTime", "source_file": "D:\\Scroller\\plethora-bit-starter\\game_bits\\tower_smash.js", "source_location": "L460"}, {"caller_nid": "tower_smash_soundcannon", "callee": "start", "source_file": "D:\\Scroller\\plethora-bit-starter\\game_bits\\tower_smash.js", "source_location": "L461"}, {"caller_nid": "tower_smash_soundcannon", "callee": "stop", "source_file": "D:\\Scroller\\plethora-bit-starter\\game_bits\\tower_smash.js", "source_location": "L461"}, {"caller_nid": "tower_smash_soundcannon", "callee": "createBuffer", "source_file": "D:\\Scroller\\plethora-bit-starter\\game_bits\\tower_smash.js", "source_location": "L463"}, {"caller_nid": "tower_smash_soundcannon", "callee": "getChannelData", "source_file": "D:\\Scroller\\plethora-bit-starter\\game_bits\\tower_smash.js", "source_location": "L464"}, {"caller_nid": "tower_smash_soundcannon", "callee": "random", "source_file": "D:\\Scroller\\plethora-bit-starter\\game_bits\\tower_smash.js", "source_location": "L465"}, {"caller_nid": "tower_smash_soundcannon", "callee": "createBufferSource", "source_file": "D:\\Scroller\\plethora-bit-starter\\game_bits\\tower_smash.js", "source_location": "L466"}, {"caller_nid": "tower_smash_soundcannon", "callee": "createGain", "source_file": "D:\\Scroller\\plethora-bit-starter\\game_bits\\tower_smash.js", "source_location": "L467"}, {"caller_nid": "tower_smash_soundcannon", "callee": "connect", "source_file": "D:\\Scroller\\plethora-bit-starter\\game_bits\\tower_smash.js", "source_location": "L468"}, {"caller_nid": "tower_smash_soundcannon", "callee": "connect", "source_file": "D:\\Scroller\\plethora-bit-starter\\game_bits\\tower_smash.js", "source_location": "L468"}, {"caller_nid": "tower_smash_soundcannon", "callee": "start", "source_file": "D:\\Scroller\\plethora-bit-starter\\game_bits\\tower_smash.js", "source_location": "L469"}, {"caller_nid": "tower_smash_soundcannon", "callee": "stop", "source_file": "D:\\Scroller\\plethora-bit-starter\\game_bits\\tower_smash.js", "source_location": "L469"}, {"caller_nid": "tower_smash_soundimpact", "callee": "createBuffer", "source_file": "D:\\Scroller\\plethora-bit-starter\\game_bits\\tower_smash.js", "source_location": "L475"}, {"caller_nid": "tower_smash_soundimpact", "callee": "getChannelData", "source_file": "D:\\Scroller\\plethora-bit-starter\\game_bits\\tower_smash.js", "source_location": "L476"}, {"caller_nid": "tower_smash_soundimpact", "callee": "random", "source_file": "D:\\Scroller\\plethora-bit-starter\\game_bits\\tower_smash.js", "source_location": "L479"}, {"caller_nid": "tower_smash_soundimpact", "callee": "pow", "source_file": "D:\\Scroller\\plethora-bit-starter\\game_bits\\tower_smash.js", "source_location": "L479"}, {"caller_nid": "tower_smash_soundimpact", "callee": "createBufferSource", "source_file": "D:\\Scroller\\plethora-bit-starter\\game_bits\\tower_smash.js", "source_location": "L481"}, {"caller_nid": "tower_smash_soundimpact", "callee": "createBiquadFilter", "source_file": "D:\\Scroller\\plethora-bit-starter\\game_bits\\tower_smash.js", "source_location": "L482"}, {"caller_nid": "tower_smash_soundimpact", "callee": "createGain", "source_file": "D:\\Scroller\\plethora-bit-starter\\game_bits\\tower_smash.js", "source_location": "L484"}, {"caller_nid": "tower_smash_soundimpact", "callee": "connect", "source_file": "D:\\Scroller\\plethora-bit-starter\\game_bits\\tower_smash.js", "source_location": "L485"}, {"caller_nid": "tower_smash_soundimpact", "callee": "connect", "source_file": "D:\\Scroller\\plethora-bit-starter\\game_bits\\tower_smash.js", "source_location": "L485"}, {"caller_nid": "tower_smash_soundimpact", "callee": "connect", "source_file": "D:\\Scroller\\plethora-bit-starter\\game_bits\\tower_smash.js", "source_location": "L485"}, {"caller_nid": "tower_smash_soundimpact", "callee": "start", "source_file": "D:\\Scroller\\plethora-bit-starter\\game_bits\\tower_smash.js", "source_location": "L486"}, {"caller_nid": "tower_smash_soundimpact", "callee": "stop", "source_file": "D:\\Scroller\\plethora-bit-starter\\game_bits\\tower_smash.js", "source_location": "L486"}, {"caller_nid": "tower_smash_soundscore", "callee": "createOscillator", "source_file": "D:\\Scroller\\plethora-bit-starter\\game_bits\\tower_smash.js", "source_location": "L492"}, {"caller_nid": "tower_smash_soundscore", "callee": "createGain", "source_file": "D:\\Scroller\\plethora-bit-starter\\game_bits\\tower_smash.js", "source_location": "L493"}, {"caller_nid": "tower_smash_soundscore", "callee": "connect", "source_file": "D:\\Scroller\\plethora-bit-starter\\game_bits\\tower_smash.js", "source_location": "L494"}, {"caller_nid": "tower_smash_soundscore", "callee": "connect", "source_file": "D:\\Scroller\\plethora-bit-starter\\game_bits\\tower_smash.js", "source_location": "L494"}, {"caller_nid": "tower_smash_soundscore", "callee": "setValueAtTime", "source_file": "D:\\Scroller\\plethora-bit-starter\\game_bits\\tower_smash.js", "source_location": "L496"}, {"caller_nid": "tower_smash_soundscore", "callee": "exponentialRampToValueAtTime", "source_file": "D:\\Scroller\\plethora-bit-starter\\game_bits\\tower_smash.js", "source_location": "L497"}, {"caller_nid": "tower_smash_soundscore", "callee": "setValueAtTime", "source_file": "D:\\Scroller\\plethora-bit-starter\\game_bits\\tower_smash.js", "source_location": "L498"}, {"caller_nid": "tower_smash_soundscore", "callee": "exponentialRampToValueAtTime", "source_file": "D:\\Scroller\\plethora-bit-starter\\game_bits\\tower_smash.js", "source_location": "L499"}, {"caller_nid": "tower_smash_soundscore", "callee": "start", "source_file": "D:\\Scroller\\plethora-bit-starter\\game_bits\\tower_smash.js", "source_location": "L500"}, {"caller_nid": "tower_smash_soundscore", "callee": "stop", "source_file": "D:\\Scroller\\plethora-bit-starter\\game_bits\\tower_smash.js", "source_location": "L500"}, {"caller_nid": "tower_smash_soundvictory", "callee": "forEach", "source_file": "D:\\Scroller\\plethora-bit-starter\\game_bits\\tower_smash.js", "source_location": "L506"}, {"caller_nid": "tower_smash_destroy", "callee": "clearTimeout", "source_file": "D:\\Scroller\\plethora-bit-starter\\game_bits\\tower_smash.js", "source_location": "L524"}, {"caller_nid": "tower_smash_destroy", "callee": "clearTimeout", "source_file": "D:\\Scroller\\plethora-bit-starter\\game_bits\\tower_smash.js", "source_location": "L525"}, {"caller_nid": "tower_smash_destroy", "callee": "clearTimeout", "source_file": "D:\\Scroller\\plethora-bit-starter\\game_bits\\tower_smash.js", "source_location": "L526"}, {"caller_nid": "tower_smash_destroy", "callee": "_unbindInput", "source_file": "D:\\Scroller\\plethora-bit-starter\\game_bits\\tower_smash.js", "source_location": "L531"}, {"caller_nid": "tower_smash_destroy", "callee": "remove", "source_file": "D:\\Scroller\\plethora-bit-starter\\game_bits\\tower_smash.js", "source_location": "L536"}, {"caller_nid": "tower_smash_destroy", "callee": "remove", "source_file": "D:\\Scroller\\plethora-bit-starter\\game_bits\\tower_smash.js", "source_location": "L537"}, {"caller_nid": "tower_smash_destroy", "callee": "remove", "source_file": "D:\\Scroller\\plethora-bit-starter\\game_bits\\tower_smash.js", "source_location": "L537"}, {"caller_nid": "tower_smash_destroy", "callee": "remove", "source_file": "D:\\Scroller\\plethora-bit-starter\\game_bits\\tower_smash.js", "source_location": "L537"}, {"caller_nid": "tower_smash_destroy", "callee": "close", "source_file": "D:\\Scroller\\plethora-bit-starter\\game_bits\\tower_smash.js", "source_location": "L544"}]}