{"nodes": [{"id": "d_scroller_plethora_bit_starter_zip_build_surrealutopia_js", "label": "surrealutopia.js", "file_type": "code", "source_file": "D:\\Scroller\\plethora-bit-starter\\zip-build\\surrealutopia.js", "source_location": "L1"}, {"id": "surrealutopia_init", "label": "init()", "file_type": "code", "source_file": "D:\\Scroller\\plethora-bit-starter\\zip-build\\surrealutopia.js", "source_location": "L10"}, {"id": "surrealutopia_pause", "label": "pause()", "file_type": "code", "source_file": "D:\\Scroller\\plethora-bit-starter\\zip-build\\surrealutopia.js", "source_location": "L270"}, {"id": "surrealutopia_resume", "label": "resume()", "file_type": "code", "source_file": "D:\\Scroller\\plethora-bit-starter\\zip-build\\surrealutopia.js", "source_location": "L271"}], "edges": [{"source": "d_scroller_plethora_bit_starter_zip_build_surrealutopia_js", "target": "surrealutopia_init", "relation": "contains", "confidence": "EXTRACTED", "source_file": "D:\\Scroller\\plethora-bit-starter\\zip-build\\surrealutopia.js", "source_location": "L10", "weight": 1.0}, {"source": "d_scroller_plethora_bit_starter_zip_build_surrealutopia_js", "target": "surrealutopia_pause", "relation": "contains", "confidence": "EXTRACTED", "source_file": "D:\\Scroller\\plethora-bit-starter\\zip-build\\surrealutopia.js", "source_location": "L270", "weight": 1.0}, {"source": "d_scroller_plethora_bit_starter_zip_build_surrealutopia_js", "target": "surrealutopia_resume", "relation": "contains", "confidence": "EXTRACTED", "source_file": "D:\\Scroller\\plethora-bit-starter\\zip-build\\surrealutopia.js", "source_location": "L271", "weight": 1.0}], "raw_calls": [{"caller_nid": "surrealutopia_init", "callee": "loadScript", "source_file": "D:\\Scroller\\plethora-bit-starter\\zip-build\\surrealutopia.js", "source_location": "L13"}, {"caller_nid": "surrealutopia_init", "callee": "createElement", "source_file": "D:\\Scroller\\plethora-bit-starter\\zip-build\\surrealutopia.js", "source_location": "L15"}, {"caller_nid": "surrealutopia_init", "callee": "getContext", "source_file": "D:\\Scroller\\plethora-bit-starter\\zip-build\\surrealutopia.js", "source_location": "L18"}, {"caller_nid": "surrealutopia_init", "callee": "getDims", "source_file": "D:\\Scroller\\plethora-bit-starter\\zip-build\\surrealutopia.js", "source_location": "L45"}, {"caller_nid": "surrealutopia_init", "callee": "max", "source_file": "D:\\Scroller\\plethora-bit-starter\\zip-build\\surrealutopia.js", "source_location": "L46"}, {"caller_nid": "surrealutopia_init", "callee": "max", "source_file": "D:\\Scroller\\plethora-bit-starter\\zip-build\\surrealutopia.js", "source_location": "L47"}, {"caller_nid": "surrealutopia_init", "callee": "max", "source_file": "D:\\Scroller\\plethora-bit-starter\\zip-build\\surrealutopia.js", "source_location": "L51"}, {"caller_nid": "surrealutopia_init", "callee": "floor", "source_file": "D:\\Scroller\\plethora-bit-starter\\zip-build\\surrealutopia.js", "source_location": "L51"}, {"caller_nid": "surrealutopia_init", "callee": "max", "source_file": "D:\\Scroller\\plethora-bit-starter\\zip-build\\surrealutopia.js", "source_location": "L52"}, {"caller_nid": "surrealutopia_init", "callee": "floor", "source_file": "D:\\Scroller\\plethora-bit-starter\\zip-build\\surrealutopia.js", "source_location": "L52"}, {"caller_nid": "surrealutopia_init", "callee": "setSize", "source_file": "D:\\Scroller\\plethora-bit-starter\\zip-build\\surrealutopia.js", "source_location": "L57"}, {"caller_nid": "surrealutopia_init", "callee": "appendChild", "source_file": "D:\\Scroller\\plethora-bit-starter\\zip-build\\surrealutopia.js", "source_location": "L59"}, {"caller_nid": "surrealutopia_init", "callee": "onDestroy", "source_file": "D:\\Scroller\\plethora-bit-starter\\zip-build\\surrealutopia.js", "source_location": "L60"}, {"caller_nid": "surrealutopia_init", "callee": "clone", "source_file": "D:\\Scroller\\plethora-bit-starter\\zip-build\\surrealutopia.js", "source_location": "L74"}, {"caller_nid": "surrealutopia_init", "callee": "createCanvas2D", "source_file": "D:\\Scroller\\plethora-bit-starter\\zip-build\\surrealutopia.js", "source_location": "L156"}, {"caller_nid": "surrealutopia_init", "callee": "listen", "source_file": "D:\\Scroller\\plethora-bit-starter\\zip-build\\surrealutopia.js", "source_location": "L159"}, {"caller_nid": "surrealutopia_init", "callee": "listen", "source_file": "D:\\Scroller\\plethora-bit-starter\\zip-build\\surrealutopia.js", "source_location": "L178"}, {"caller_nid": "surrealutopia_init", "callee": "listen", "source_file": "D:\\Scroller\\plethora-bit-starter\\zip-build\\surrealutopia.js", "source_location": "L215"}, {"caller_nid": "surrealutopia_init", "callee": "raf", "source_file": "D:\\Scroller\\plethora-bit-starter\\zip-build\\surrealutopia.js", "source_location": "L221"}, {"caller_nid": "surrealutopia_init", "callee": "ready", "source_file": "D:\\Scroller\\plethora-bit-starter\\zip-build\\surrealutopia.js", "source_location": "L267"}]}